awmctrl.py
awmctrl-0.1.dist-info/LICENSE.txt
awmctrl-0.1.dist-info/METADATA
awmctrl-0.1.dist-info/WHEEL
awmctrl-0.1.dist-info/entry_points.txt
awmctrl-0.1.dist-info/top_level.txt
awmctrl-0.1.dist-info/RECORD
